luciferml/__init__.py
luciferml/preprocessing.py
luciferml/supervised/__init__.py
luciferml/supervised/classification.py
luciferml/supervised/regression.py
luciferml/supervised/utils/__init__.py
luciferml/supervised/utils/best.py
luciferml/supervised/utils/configs.py
luciferml/supervised/utils/predictors.py
luciferml/supervised/utils/preprocesser.py
luciferml/supervised/utils/validator.py
luciferml/supervised/utils/tuner/luciferml_tuner.py
luciferml/supervised/utils/tuner/optuna/optuna_base.py
luciferml/supervised/utils/tuner/optuna/objectives/classification_objectives.py
luciferml/supervised/utils/tuner/optuna/objectives/regression_objectives.py
lucifer_ml-0.0.80.dist-info/LICENSE
lucifer_ml-0.0.80.dist-info/METADATA
lucifer_ml-0.0.80.dist-info/WHEEL
lucifer_ml-0.0.80.dist-info/top_level.txt
lucifer_ml-0.0.80.dist-info/RECORD
