Metadata-Version: 2.1
Name: lucifer-ml
Version: 0.0.80
Summary: Automated ML by d4rk-lucif3r
Home-page: https://github.com/d4rk-lucif3r/LuciferML
Author: Arsh Anwar
Author-email: lucifer78908@gmail.com
License: MIT
Keywords: luciferML,AutoML,Python
Platform: UNKNOWN
Classifier: Development Status :: 3 - Alpha
Classifier: Intended Audience :: Developers
Classifier: Topic :: Software Development :: Build Tools
Classifier: License :: OSI Approved :: MIT License
Classifier: Programming Language :: Python :: 3
Classifier: Programming Language :: Python :: 3.4
Classifier: Programming Language :: Python :: 3.5
Classifier: Programming Language :: Python :: 3.6
License-File: LICENSE
Requires-Dist: numpy
Requires-Dist: pandas
Requires-Dist: scipy
Requires-Dist: seaborn
Requires-Dist: matplotlib
Requires-Dist: scikit-learn
Requires-Dist: imblearn
Requires-Dist: xgboost
Requires-Dist: tensorflow
Requires-Dist: catboost
Requires-Dist: lightgbm
Requires-Dist: optuna
Requires-Dist: shap
Requires-Dist: colorama
